jwtserver/__init__.py
jwtserver/alembic.ini
jwtserver/api/__init__.py
jwtserver/api/add_later/__init__.py
jwtserver/api/add_later/check_code.py
jwtserver/api/add_later/send_code.py
jwtserver/api/add_later/types_model.py
jwtserver/api/api_v1/__init__.py
jwtserver/api/api_v1/api.py
jwtserver/api/api_v1/endpoints/__init__.py
jwtserver/api/api_v1/endpoints/items.py
jwtserver/api/api_v1/endpoints/login.py
jwtserver/api/api_v1/endpoints/users.py
jwtserver/api/api_v1/endpoints/utils.py
jwtserver/api/deps.py
jwtserver/app.py
jwtserver/commands.py
jwtserver/core/celery_app.py
jwtserver/core/config.py
jwtserver/core/security.py
jwtserver/crud/__init__.py
jwtserver/crud/base.py
jwtserver/crud/crud_item.py
jwtserver/crud/crud_user.py
jwtserver/db/__init__.py
jwtserver/db/base.py
jwtserver/db/base_class.py
jwtserver/db/init_db.py
jwtserver/db/session.py
jwtserver/default.ini
jwtserver/email-templates/build/new_account.html
jwtserver/email-templates/build/reset_password.html
jwtserver/email-templates/build/test_email.html
jwtserver/email-templates/src/new_account.mjml
jwtserver/email-templates/src/reset_password.mjml
jwtserver/email-templates/src/test_email.mjml
jwtserver/middlewares/stock.py
jwtserver/migration/__init__.py
jwtserver/migration/env.py
jwtserver/migration/README
jwtserver/migration/script.py.mako
jwtserver/migration/versions/98f3d19d2c0d_initial.py
jwtserver/models/__init__.py
jwtserver/models/item.py
jwtserver/models/user.py
jwtserver/models.py
jwtserver/old_dependencies/__init__.py
jwtserver/old_dependencies/init_redis.py
jwtserver/old_dependencies/session_db.py
jwtserver/pytest.ini
jwtserver/recaptcha/__init__.py
jwtserver/recaptcha/google.py
jwtserver/schemas/__init__.py
jwtserver/schemas/item.py
jwtserver/schemas/msg.py
jwtserver/schemas/token.py
jwtserver/schemas/user.py
jwtserver/schemas.py
jwtserver/server.py
jwtserver/test_main_.http
jwtserver/tests/__init__.py
jwtserver/tests/config.ini
jwtserver/tests/conftest.py
jwtserver/tests/depends.py
jwtserver-0.0.40.dist-info/entry_points.txt
jwtserver-0.0.40.dist-info/METADATA
jwtserver-0.0.40.dist-info/WHEEL
jwtserver-0.0.40.dist-info/RECORD
