Metadata-Version: 2.1
Name: jwtserver
Version: 0.0.40
Summary: jwt authorization server
License: Apache2
Author: goltsevnet
Author-email: mark@goltsev.net
Requires-Python: >=3.8.1,<4.0.0
Classifier: Development Status :: 3 - Alpha
Classifier: Intended Audience :: Developers
Classifier: License :: OSI Approved :: Apache Software License
Classifier: License :: Other/Proprietary License
Classifier: Programming Language :: Python :: 3
Classifier: Programming Language :: Python :: 3.9
Classifier: Programming Language :: Python :: 3.10
Classifier: Programming Language :: Python :: 3.11
Classifier: Programming Language :: Python :: 3.10
Classifier: Topic :: Software Development :: Build Tools
Requires-Dist: alembic (>=1.10.2,<2.0.0)
Requires-Dist: asyncpg (==0.27.0)
Requires-Dist: celery (>=5.2.7,<6.0.0)
Requires-Dist: emails (>=0.6,<0.7)
Requires-Dist: fastapi (>=0.95.0,<0.96.0)
Requires-Dist: httpx (>=0.23.3,<0.24.0)
Requires-Dist: loguru (>=0.6.0,<0.7.0)
Requires-Dist: passlib (==1.7.4)
Requires-Dist: phonenumbers (>=8.13.7,<8.14.0)
Requires-Dist: psycopg2 (==2.9.5)
Requires-Dist: pydantic[email] (>=1.10.6,<2.0.0)
Requires-Dist: pytest (==7.2.2)
Requires-Dist: python-dotenv (>=1.0.0,<2.0.0)
Requires-Dist: python-jose[cryptography] (>=3.3.0,<4.0.0)
Requires-Dist: python-multipart (>=0.0.6,<0.0.7)
Requires-Dist: redis[hiredis] (>=4.5.1,<5.0.0)
Requires-Dist: setuptools (>=67.6.0,<67.7.0)
Requires-Dist: sqlalchemy (>=2.0.7,<3.0.0)
Requires-Dist: sqlalchemy_utils (>=0.40.0,<0.41.0)
Requires-Dist: starlette (>=0.26.1,<0.27.0)
Requires-Dist: uvicorn (>=0.21.1,<0.22.0)
Project-URL: GitHub, https://github.com/darkdealnet/jwtserver
